<?xml version="1.0" encoding="utf-8"?>
<GTMessageFactory lang="en">
	<GTMessage key="NO_SUCH_COMMAND">
		<content>
			<h4>No such command : « #1 » inconnue</h4>
			<p>I don't know the command « #1 ».</p>
		</content>
	</GTMessage>
	<GTMessage key="ARITY">
		<content>
			<h4>Incorrect parameters number</h4>
			<p>La commande <span class="command">#1</span> doit être suivie d'exactement <b>#2</b> nombre(s).</p>
			<br/>
			<p>Conseil : si un calcul algébrique contient une espace, il doit être placé entre parenthèses.</p>
		</content>
	</GTMessage>
	<GTMessage key="PROCEDURE_ARITY">
		<content>
			<h4>Nombre d'arguments incorrect</h4>
			<p>La procédure <span class="procedure">#1</span> doit être suivie d'exactement <b>#2</b> nombre(s).</p>
			<br/>
			<p>Conseil : si un calcul algébrique contient une espace, il doit être placé entre parenthèses.</p>
		</content>
	</GTMessage>
	<GTMessage key="CONFLICT_FUNCTION">
		<content>
			<h4>Dénomination conflictuelle</h4>
			<p>Le mot <span class="function">#1</span> désigne déjà une fonction.</p>
			<p>Merci de choisir un autre nom.</p>
		</content>
	</GTMessage>
	<GTMessage key="CONFLICT_PROCEDURE">
		<content>
			<h4>Dénomination conflictuelle</h4>
			<p>Le mot <span class="procedure">#1</span> désigne déjà une procédure existante.</p>
			<p>Merci de choisir un autre nom.</p>
		</content>
	</GTMessage>
	<GTMessage key="CONFLICT_KEYWORD">
		<content>
			<h4>Dénomination conflictuelle</h4>
			<p>Le mot <span class="keyword">#1</span> est un mot réservé qui ne peut être utilisé.</p>
			<p>Merci de choisir un autre nom.</p>
		</content>
	</GTMessage>
	<GTMessage key="CONFLICT_TURTLE">
		<content>
			<h4>Dénomination conflictuelle</h4>
			<p>Le mot <span class="turtle">#1</span> désigne déjà une tortue.</p>
			<p>Merci de choisir un autre nom.</p>
		</content>
	</GTMessage>
	<GTMessage key="CONFLICT_VARIABLE">
		<content>
			<h4>Dénomination conflictuelle</h4>
			<p>Le mot <span class="varglob">#1</span> désigne déjà une variable.</p>
			<p>Merci de choisir un autre nom.</p>
		</content>
	</GTMessage>
	<GTMessage key="CONFLICT_LIBRARY">
		<content>
			<h4>Dénomination conflictuelle</h4>
			<p>Le mot <span class="library">#1</span> désigne déjà une procédure archivée dans la bibliothèque.</p>
			<p>Merci de choisir un autre nom.</p>
		</content>
	</GTMessage>
	<GTMessage key="SYMBOL_CONTAINS_DELIMITERS">
		<content>
			<h4>Dénomination interdite</h4>
			<p>Le mot « #1 » comporte un symbole d'opération, ce qui n'est pas permis.</p>
			<p>Merci de choisir un nom valide.</p>
			<br/>
			<p>Note : les symboles d'opérations sont les suivants : </p>
			<p style="text-align:center;"><b>, ; : . { } ( ) [ ] + - / * ^ % &lt; = &gt; ! &amp; | ~ " '</b></p>
		</content>
	</GTMessage>
	<GTMessage key="SYMBOL_DIGITS">
		<content>
			<h4>Dénomination interdite</h4>
			<p>Le mot« #1 » commence par un chiffre, ce qui n'est pas permis.</p>
			<p>Merci de choisir un nom valide.</p>
		</content>
	</GTMessage>
	<GTMessage key="ASSIGNMENT">
		<content>
			<h4>Usage incorrecte de la commande d'assignation</h4>
			<p>Les caractères <b>:=</b> permettent de déclarer une variable et de lui assigner une valeur.</p>
			<p>Ils doivent donc être précédés d'un nom de variable, et suivis d'un nombre ou d'un calcul algébrique.</p>
		</content>
	</GTMessage>
	<GTMessage key="ASSIGNMENT_TO_CONSTANT">
		<content>
			<h4>Dénomination interdite</h4>
			<p>Le symbole <span class="varglob">#1</span> est déjà utilisé pour désigner une constante mathématique.</p>
			<p>Merci de choisir un autre nom.</p>
		</content>
	</GTMessage>
	<GTMessage key="FUNCTION_DECLARATION">
		<content>
			<h4>Définition de fonction incorrecte</h4>
			<p>La commande <span class="keyword">def</span> doit être utilisée selon la syntaxe suivante :</p>
			<br/>
			<p><span class="keyword">def</span> f : x -> f(x)</p>
			<br/>
			<p>Exemple :</p>
			<p class="highlight"><span class="keyword">def</span> f : x -> x^2+1</p>
		</content>
	</GTMessage>
	<GTMessage key="JEP_ERROR">
		<content>
			<h4>Calcul impossible</h4>
			<p>Je ne parviens pas à effectuer le calcul « #1 ».</p>
		</content>
	</GTMessage>
	<GTMessage key="NULL_RETURNED">
		<content>
			<h4>Erreur d'évaluation</h4>
			<p>L'évaluation « #1 » ne renvoie aucun nombre.</p>
		</content>
	</GTMessage>
	<GTMessage key="JEP_NAN">	
		<content>
			<h4>Calcul impossible</h4>
			<p>Je ne parviens pas à effectuer le calcul « #1 », car le résultat ne semble pas être un nombre.</p>
			<p class="small">Vérifie que le calcul ne comporte pas de racine carrée d'un nombre négatif.</p>
		</content>
	</GTMessage>
	<GTMessage key="JEP_UNRECOGNIZED_SYMBOL">	
		<content>
			<h4>Calcul impossible</h4>
			<p>Je ne connais pas la valeur de « #1 » dans le calcul « #2 ».</p>
		</content>
	</GTMessage>
	<GTMessage key="JEP_INF">
		<content>
			<h4>Calcul impossible</h4>
			<p>Je ne parviens pas à effectuer le calcul « #1 », car il mène à des expressions infinies.</p>
			<p class="small">Vérifie que le calcul ne comporte pas une division par zéro.</p>
		</content>
	</GTMessage>
	<GTMessage key="PENCIL">
		<content>
			<h4>Usage incorrect de la commande <span class="reserved">crayon</span></h4>
			<p>La commande <span class="command">crayon</span> doit être suivie du nom d'une couleur parmi les suivantes :</p>
			<p style="text-align:center"> noir, rouge, vert, bleu, orange, jaune, rose, gris, cyan, magenta, blanc.</p>
			<br/>
			<p>La commande <span class="command">crayon</span> peut aussi être suivie du nom d'une tortue.</p>
			<p>Dans ce cas, le crayon aura la couleur de la tortue choisie.
			</p>
			<br/>
			<p>Exemples :</p>
			<div class="highlight"><span class="command">crayon</span> rouge</div>
			<div class="highlight"><span class="command">couleur</span> <span class="turtle">Achille</span></div>
			<br/>
			<p>Consulter l'aide pour plus de détails.</p>
		</content>
	</GTMessage>
	<GTMessage key="PENCIL_HEX">
		<content>
			<h4>Commande <span class="reserved">crayon</span> : couleur inconnue</h4>
			<p>Je ne connais pas la couleur « #1 ».</p>
			<br/>
			<p>La commande <span class="command">crayon</span> doit être suivie du nom d'une couleur parmi les suivantes :</p>
			<p style="text-align:center"> noir, rouge, vert, bleu, orange, jaune, rose, gris, cyan, magenta, blanc.</p>
			<br/>
			<p>La commande <span class="command">crayon</span> peut aussi être suivie du nom d'une tortue.</p>
			<p>Dans ce cas, le crayon aura la couleur de la tortue choisie.	</p>
			<p>Consulter l'aide pour plus de détails.</p>
		</content>
	</GTMessage>
	<GTMessage key="PALETTE">
		<content>
			<h4>Usage incorrect de la commande <span class="command">palette</span></h4>
			<p>La commande <span class="command">palette</span> doit être suivie du nuancier choisie (RVB, rvb, TSV ou tsv)</p>
			<p>Consulter l'aide pour plus de détails.</p>
		</content>
	</GTMessage>
	<GTMessage key="PALETTE_RGB">
		<content>
			<h4>Commande <span class="command">palette</span> : composantes RVB absentes</h4>
			<p>Les commandes <span class="command">palette</span> <span class="function">RVB</span> et <span class="command">palette</span> <span class="function">rvb</span> doivent être suivies de trois nombres.</p>
			<p>Consulter l'aide pour plus de détails.</p>
		</content>
	</GTMessage>
	<GTMessage key="PALETTE_RGB_ILLEGAL">
		<content>
			<h4>Commande <span class="command">palette</span> : composantes rvb incorrectes</h4>
			<p>La commande <span class="command">palette</span> <span class="function">rvb</span> doit être suivie de trois nombres compris entre 0 et 1.</p>
			<p>Consulter l'aide pour plus de détails.</p>
		</content>
	</GTMessage>
	<GTMessage key="PALETTE_RGB_255_ILLEGAL">
		<content>
			<h4>Commande <span class="command">palette</span> : composantes RVB incorrectes</h4>
			<p>La commande <span class="command">palette</span> <span class="function">RVB</span> doit être suivie de trois nombres entiers compris entre 0 et 255.</p>
			<p>Consulter l'aide pour plus de détails.</p>
		</content>
	</GTMessage>	
	<GTMessage key="PALETTE_HSB">
		<content>
			<h4>Commande <span class="command">palette</span> : composantes TSV absentes</h4>
			<p>Les commandes <span class="command">palette</span> <span class="function">TSV</span> et <span class="command">palette</span> <span class="function">tsv</span> doivent être suivies de trois nombres.</p>
			<p>Consulter l'aide pour plus de détails.</p>
		</content>
	</GTMessage>
	<GTMessage key="PALETTE_HSB_255_ILLEGAL">
		<content>
			<h4>Commande <span class="command">palette</span> : composantes TSV incorrectes</h4>
			<p>La commande <span class="command">palette</span> <span class="function">TSV</span> doit être suivie d'un nombre entier compris entre 0 et 360<br> et de deux nombres entiers compris entre 0 et 100.</p>
			<p>Consulter l'aide pour plus de détails.</p>
		</content>
	</GTMessage>	
	<GTMessage key="IF_THEN_ELSE">
		<content>
			<h4>Usage incorrect du branchement conditionnel <span class="keyword">si</span></h4>
			<p>La commande <span class="keyword">si</span> doit être utilisée selon l'un des modèles suivants :</p>
			<br/>
			<p><span class="keyword">si</span> <i>condition</i> <span class="keyword">alors</span> <i>instructions</i></p>
			<p><span class="keyword">si</span> <i>condition</i> <span class="keyword">alors</span> <i>instructions1</i> <span class="keyword">sinon</span> <i>instructions2</i></p>
			<br/>
			<p>Note : les blocs d'instruction doivent être placés entre crochets.</p>
			<br/>
			<p class="emph">Exemple :</p>
			<div class="highlight"><span class="keyword">si</span> (<span class="varglob">x</span>&gt;0) <span class="keyword">alors</span> [<span class="command">av</span> 50] <span class="keyword">sinon</span> [<span class="command">re</span> 50]</div>
			<br/>
			<p>Consulter l'aide pour plus de détails.</p>
		</content>
	</GTMessage>
	<GTMessage key="REPEAT">
		<content>
			<h4>Usage incorrect de la boucle <span class="keyword">rep</span></h4>
			<p>La commande <span class="keyword">rep</span> doit être suivie d'un nombre et d'un bloc de commandes entre crochets.</p>
			<br/>
			<p class="emph">Exemple :</p>
			<div class="highlight"><span class="keyword">rep</span> 4 [<span class="command">av</span> 50 ; <span class="command">td</span> 90]</div>
			<br/>
			<p>Consulter l'aide pour plus de détails.</p>
		</content>
	</GTMessage>
	<GTMessage key="WHILE">
		<content>
			<h4>Usage incorrect de la boucle <span class="keyword">tant_que</span></h4>
			<p>La commande <span class="keyword">tant_que</span> doit être utilisée selon le modèle suivant :</p>
			<br/>
			<p><span class="keyword">tant_que</span> <i>condition</i> <i>instructions</i></p>
			<br/>
			<p>Note : les blocs d'instruction doivent être placés entre crochets.</p>
			<br/>
			<p class="emph">Exemple :</p>
			<div class="highlight"><span class="varglob">x</span>:=10; <span class="keyword">tant_que</span> (<span class="varglob">x</span>&lt;100) [<span class="command">av</span> x; <span class="command">td</span> 90; <span class="varglob">x</span>:=<span class="varglob">x</span>+10]</div>
			<br/>
			<p>Consulter l'aide pour plus de détails.</p>
		</content>
	</GTMessage>
	<GTMessage key="NOT_3D">
		<content>
			<h4>Commandes non disponibles</h4>
			<p>Les commandes <span class="command">pvh</span>, <span class="command">pvb</span>, <span class="command">pvg</span> et <span class="command">pvd</span> ne sont disponibles que pour les géométries à (au moins) trois dimensions.</p>
		</content>
	</GTMessage>
	<GTMessage key="NOT_4D">
		<content>
			<h4>Commandes non disponibles</h4>
			<p>Les commandes <span class="command">pvxy</span>, <span class="command">pvxz</span> et <span class="command">pvyz</span> ne sont disponibles que pour la géométrie à quatre dimensions.</p>
		</content>
	</GTMessage>
	<GTMessage key="FILLING">
		<content>
			<h4>Usage incorrect de la commande <span class="keyword">remplis</span></h4>
			<br/>
			<p>La commande <span class="keyword">remplis</span> doit être suivie d'un bloc de commandes entre crochets.</p>
			<br/>
			<p>Exemple :</p>
			<div class="highlight"><span class="keyword">remplis</span> [ <span class="keyword">rep</span> 4 [<span class="command">av</span> 50 ; <span class="command">td</span> 90] ]</div>
			<br/>
			<p>Consulter l'aide pour plus de détails.</p>
		</content>
	</GTMessage>
	<GTMessage key="FILLING_REDONDANT">
		<content>
			<h4>Conflit impliquant la commande <span class="keyword">remplis</span></h4>
			<p>Une commande <span class="keyword">remplis</span> est appelée à l'intérieur d'une instruction <span class="keyword">remplis</span>.</p>
		</content>
	</GTMessage>
	<GTMessage key="NON_FLAT_FILLING">
		<content>
			<h4>Dans la commande <span class="keyword">remplis</span></h4>
			<p>Je ne sais pas comment colorier un polygone qui n'est pas contenu dans un plan.</p>
		</content>
	</GTMessage>
	<GTMessage key="TELEPORTATION">
		<content>
			<h4>Usage incorrect de la commande <span class="command">tlp</span></h4>
			<p>La géométrie « #1 » est à #2 dimensions. <br> La commande <span class="command">tlp</span> doit donc être suivie d'exactement #2 nombres.</p>
			<br/>
			<p>Exemple (géométrie à deux dimensions) :</p>
			<div class="highlight"><span class="command">tlp</span> 100 100</div>
		</content>
	</GTMessage>
	<GTMessage key="HP_TELEPORTATION">
		<content>
			<h4>Téléportation impossible</h4>
			<p>Le point de coordonnées #1 n'appartient pas à la géométrie « #2 ».</p>
			<br/>
			<p>Consulter l'aide pour plus de détails.</p>
		</content>
	</GTMessage>
	<GTMessage key="TRANSPORT">
		<content>
			<h4>Erreurs de calcul</h4>
			<p>Les calculs pour déplacer la tortue ont échoué.</p>
			<p>Ceci est probablement dû au fait que la tortue est trop éloigné de son point de départ.</p>
			 <br/>
			<p>Détails : #1</p>
		</content>
	</GTMessage>
	<GTMessage key="VISE">
		<content>
			<h4>Usage incorrect de la commande <span class="command">vise</span></h4>
			<p>La commande <span class="command">vise</span> doit être suivie du nom (ou du numéro) d'une tortue (et d'une seule).</p>
			<br/>
			<p class="emph">Exemple :</p>
			<div class="highlight"><span class="command">vise</span> <span class="turtle">Achille</span></div>
			<div class="highlight"><span class="command">vise</span> <span class="turtle">0</span></div>
		</content>
	</GTMessage>
	<GTMessage key="IMITATE">
		<content>
			<h4>Usage incorrect de la commande <span class="command">imite</span></h4>
			<p>La commande <span class="command">imite</span> doit être suivie du nom (ou du numéro) d'une tortue (et d'une seule).</p>
		</content>
	</GTMessage>
	<GTMessage key="TURTLE_SELECTION">
		<content>
			<h4>Usage incorrect de la commande <span class="keyword">à</span></h4>
			<p>Le mot-clef <span class="keyword">à</span> doit être suivie des noms (ou des numéros) d'une ou de plusieurs tortue, ou bien du mot <span class="keyword">toutes</span>.</p>
			<br/>
			<p>Consulter l'aide pour plus de détails.</p>
		</content>
	</GTMessage>
	<GTMessage key="LAST_TURTLE">
		<content>
			<h4>Impossible de retirer <span class="turtle">#1</span></h4>
			<p>Il n'est pas possible de retirer <span class="turtle">#1</span>, car c'est la seule tortue actuellement définie.</p>
		</content>
	</GTMessage>
	<GTMessage key="TURTLE_INDEX">
		<content>
			<h4>Tortue inconnue</h4>
			<p>Aucune tortue ne porte le numéro #1.</p>
		</content>
	</GTMessage>
	<GTMessage key="NO_SUCH_TURTLE">
		<content>
			<h4>Tortue inconnue</h4>
			<p>Aucune tortue ne se nomme « #1 ».</p>
			<p>Il s'agit peut-être d'une erreur de frappe ?</p>
		</content>
	</GTMessage>
	<GTMessage key="WRONG_PASSWORD">
		<content>
			<h4>Mot de passe incorrect</h4>
			<br/>
			<p>Attention aux majuscules et minuscules lors de la saisie du mot de passe.</p>
			<br/>
		</content>
	</GTMessage>
	<GTMessage key="MISMATCHING_PASSWORD">
		<content>
			<h4>Les mots de passe saisis sont différents</h4>
			<br/>
			<p>Attention aux majuscules et minuscules lors de la saisie du mot de passe.</p>
			<br/>
		</content>
	</GTMessage>
	<GTMessage key="MANIPULATION">
		<content>
			<h4>Usage incorrect de la commande <span class="keyword">mg</span></h4>
			<p>Consulter l'aide pour plus de détails.</p>
		</content>
	</GTMessage>
	<GTMessage key="MANIPULATION_UNAVAILABLE">
		<content>
			<h4>Commande <span class="keyword">mg</span> : manipulation impossible</h4>
			<p>La géométrie « #2 » n'autorise pas la manipulation indiquée par le mot-clef « #1 ».</p> 
			<p>Consulter l'aide pour plus de détails.</p>
		</content>
	</GTMessage>
	<GTMessage key="MANIPULATION_UNKNOWN">
		<content>
			<h4>Commande <span class="keyword">mg</span> : mot-clef inconnu</h4>
			<p>Il n'y a pas de manipulation de l'espace graphique associée au mot « #1 ».</p>
			<p>Il s'agit peut-être d'une erreur de frappe ?</p>
			<br>
			<p>Consulter l'aide pour plus de détails.</p>
		</content>
	</GTMessage>
	<GTMessage key="MISMATCHING_BRACKETS">
		<content>
			<h4>Parenthésage incohérent</h4>
			<p>TODO</p>
		</content>
	</GTMessage>
	<GTMessage key="MISSING_OPENING_ROUND_BRACKET">
		<content>
			<h4>Erreur de parenthésage</h4>
			<p>Une parenthèse fermante ')' ne termine aucune expression.</p>
		</content>
	</GTMessage>
	<GTMessage key="MISSING_CLOSING_ROUND_BRACKET">
		<content>
			<h4>Erreur de parenthésage</h4>
			<p>Une parenthèse ouvrante '(' n'est pas correctement fermée.</p>
		</content>
	</GTMessage>
	<GTMessage key="MISSING_OPENING_BRACKET">
		<content>
			<h4>Erreur de parenthésage</h4>
			<p>Un crochet fermant ']' ne termine aucune expression.</p>
		</content>
	</GTMessage>
	<GTMessage key="MISSING_CLOSING_BRACKET">
		<content>
			<h4>Erreur de parenthésage</h4>
			<p>Un crochet ouvrant '[' n'est pas correctement fermé;.</p>
		</content>
	</GTMessage>
	<GTMessage key="MISSING_OPENING_CURLY_BRACKET">
		<content>
			<h4>Erreur de parenthésage</h4>
			<p>Une accolade fermante '}' ne termine aucune expression.</p>
		</content>
	</GTMessage>
	<GTMessage key="MISSING_CLOSING_CURLY_BRACKET">
		<content>
			<h4>Erreur de parenthésage</h4>
			<p>Une accolade ouvrante '{' n'est pas correctement fermée.</p>
		</content>
	</GTMessage>
	<GTMessage key="NO_SUCH_FIELD">
		<content>
			<h4>Case mémoire inconnu</h4>
			<p>La case mémoire « #1 » n'a pas été définie.</p>
			<p>Appuyer sur la touche F12 pour créer une nouvelle case mémoire.</p>
		</content>
	</GTMessage>
	<GTMessage key="CANNOT_DELETE_A_FIELD">
		<content>
			<h4>Mauvais usage de la commande <span class="keyword">eff</span></h4>
			<p>La case mémoire « #1 » ne peut être supprimée à l'aide dela commande <span class="keyword">eff</span>.</p>
			<p>Appuyer sur la touche F12 pour supprimer cette case mémoire.</p>
		</content>
	</GTMessage>
	<GTMessage key="STORE">
		<content>
			<h4>Usage incorrect de la commande <span class="keyword">retiens</span></h4>
			<p>La syntaxe doit suivre le modèle : <span class="keyword">retiens</span> <span class="function">case</span> = x, où <br>
			<span class="function">case</span> est le nom d'une case mémoire et x une valeur numérique.</p>
			<br>
			<p>Consulter l'aide pour plus de détails.</p>
		</content>
	</GTMessage>
	<GTMessage key="LOOP">
		<content>
			<h4>Usage incorrect de la commande <span class="keyword">boucle</span></h4>
			<p>La syntaxe doit suivre le modèle</p>
			<br>
			<p style="text-align:center"><span class="keyword">boucle</span> <i>var</i> <span class="keyword">de</span> <i>n</i><sub>min</sub> <span class="keyword">à</span> <i>n</i><sub>max</sub></p>
			<br>
			<p>où <i>n</i><sub>min</sub> et <i>n</i><sub>max</sub> désignent deux nombres entiers.</p>
			<br>
			<p>Exemple :</p>
			<p class="highlight">
			<span class="keyword">boucle</span> k <span class="keyword">de</span> 1 <span class="keyword">à</span> 10 [ <span class="keyword">av</span> k*20; <span class="command">td</span> 90 ; <span class="keyword">écris</span> k]
			</p>
			<br>
			<p>Consulter l'aide pour plus de détails.</p>
		</content>
	</GTMessage>
	<GTMessage key="QUATERNION_FUNCTION">
		<content>
			<h4>Usage incorrect de la fonctions <span class="keyword">GET_QUATERNION_FUNCTION</span></h4>
			<p>(TODO : à rédiger)</p>
			<br>
			<p>Consulter l'aide pour plus de détails.</p>
		</content>
	</GTMessage>
	<GTMessage key="NO_SUCH_ARRAY">
		<content>
			<h4>Affectation</h4>
			<p>Je ne connais pas la liste #1.</p>
			<br>
			<p>Consulter l'aide pour plus de détails.</p>
		</content>
	</GTMessage>
	<GTMessage key="NO_SUCH_ELEMENT">
		<content>
			<h4>Affectation</h4>
			<p>La liste #1 n'a pas de valeur pour l'indice #2.</p>
			<br>
			<p>Consulter l'aide pour plus de détails.</p>
		</content>
	</GTMessage>
	<GTMessage key="ELEMENT_ILLEGAL_CALL">
		<content>
			<h4>Illegal_call</h4>
			<p>(TODO : à rédiger)</p>
		</content>
	</GTMessage>
	<GTMessage key="ADD">
		<content>
			<h4>Usage incorrect de la fonctions <span class="keyword">ajoute</span></h4>
		</content>
	</GTMessage>
	<GTMessage key="FOR_EACH">
		<content>
			<h4>Usage incorrect de la commande <span class="keyword">pour_chaque</span></h4>
			<p>La syntaxe doit suivre le modèle : <span class="keyword">pour_chaque</span> <i>élément</i> <span class="keyword">dans</span><span class="function">$Liste</span> <i>instructions</i>.
			</p>
		</content>
	</GTMessage>
	<GTMessage key="PAUSE_NEGATIVE_TIME">
		<content>
			<h4>Commande <span class="keyword">pause</span> : je ne peux pas faire une pause d'un temps négatif (=#1).</h4>
		</content>
	</GTMessage>
	
	<GTMessage key="STACK_OVERFLOW">
		<content>
			<h4>Une procédure boucle sur elle-même et a provoqué un dépassement de pile !</h4>
			<p>Une procédure boucle sur elle-même et a provoqué un dépassement de pile !</p>
		</content>
	</GTMessage>
</GTMessageFactory>
